{"index.md":"MZ8qIumv","page.md":"rPWxO_MK","page_1.md":"Fe_Jxvh5","page_index.md":"DltdXLCy","pages_about.md":"D_pmhMjU","pages_archives.md":"CtMlG9Rr","pages_categories.md":"C9blnyau","pages_categories_随便说说.md":"DiLliYYL","pages_cc.md":"DBnEbOKP","pages_index.md":"BoDo8w49","pages_link.md":"D3luNj9V","pages_privacy.md":"qeX91-zY","pages_project.md":"BcYMR-OF","pages_tags.md":"CXH5Y9Oc","pages_tags_hello.md":"-LQ8VhU9","pages_tags_网站建设.md":"CwDjdERN","posts_2024_1010.md":"Cldy7_II","posts_2025_0109.md":"C35l9WXr"}
